{
  "totalEnterprises": 2575,
  "englandTotal": 2376615,
  "enterprisesPerCapita": 0,
  "sizeBands": [
    {
      "band": "0 to 4",
      "local": 1915,
      "localPct": 74.2,
      "englandPct": 78.6
    },
    {
      "band": "5 to 9",
      "local": 345,
      "localPct": 13.4,
      "englandPct": 10.8
    },
    {
      "band": "10 to 19",
      "local": 175,
      "localPct": 6.8,
      "englandPct": 5.6
    },
    {
      "band": "20 to 49",
      "local": 95,
      "localPct": 3.7,
      "englandPct": 3.1
    },
    {
      "band": "50 to 99",
      "local": 30,
      "localPct": 1.2,
      "englandPct": 1.1
    },
    {
      "band": "100 to 249",
      "local": 15,
      "localPct": 0.6,
      "englandPct": 0.5
    },
    {
      "band": "250 to 499",
      "local": 5,
      "localPct": 0.2,
      "englandPct": 0.2
    }
  ],
  "trend": [
    {
      "year": "2023",
      "count": 2515
    },
    {
      "year": "2024",
      "count": 2570
    },
    {
      "year": "2025",
      "count": 2575
    }
  ],
  "growthRate": 2.4
}