{
  "births": 290,
  "deaths": 235,
  "active": 2705,
  "year": "2024",
  "birthRate": 10.7,
  "deathRate": 8.7,
  "netFormationRate": 2,
  "survivalRates": {
    "oneYear": 96.6,
    "threeYear": 62.1,
    "fiveYear": 44.8
  },
  "trend": [
    {
      "year": "2019",
      "births": 290,
      "deaths": 225,
      "active": 2595
    },
    {
      "year": "2020",
      "births": 255,
      "deaths": 280,
      "active": 2660
    },
    {
      "year": "2021",
      "births": 285,
      "deaths": 280,
      "active": 2665
    },
    {
      "year": "2024",
      "births": 290,
      "deaths": 235,
      "active": 2705
    }
  ],
  "englandBirthRate": 11.2,
  "englandDeathRate": 9.9,
  "englandSurvival5yr": 40.7
}