{
  "sectors": [
    {
      "sector": "Agriculture, forestry & fishing",
      "sicSection": "A",
      "employment": 70,
      "localShare": 0.0021,
      "nationalShare": 0.0052,
      "lq": 0.41,
      "classification": "Under-represented"
    },
    {
      "sector": "Mining & quarrying",
      "sicSection": "B",
      "employment": 0,
      "localShare": 0,
      "nationalShare": 0.0007,
      "lq": 0,
      "classification": "Under-represented"
    },
    {
      "sector": "Manufacturing",
      "sicSection": "C",
      "employment": 2370,
      "localShare": 0.0725,
      "nationalShare": 0.0713,
      "lq": 1.02,
      "classification": "Average"
    },
    {
      "sector": "Electricity, gas & air conditioning",
      "sicSection": "D",
      "employment": 0,
      "localShare": 0,
      "nationalShare": 0.0036,
      "lq": 0,
      "classification": "Under-represented"
    },
    {
      "sector": "Water supply & waste management",
      "sicSection": "E",
      "employment": 140,
      "localShare": 0.0043,
      "nationalShare": 0.0071,
      "lq": 0.61,
      "classification": "Under-represented"
    },
    {
      "sector": "Construction",
      "sicSection": "F",
      "employment": 1575,
      "localShare": 0.0482,
      "nationalShare": 0.0489,
      "lq": 0.98,
      "classification": "Average"
    },
    {
      "sector": "Wholesale & retail trade",
      "sicSection": "G",
      "employment": 4900,
      "localShare": 0.1499,
      "nationalShare": 0.1372,
      "lq": 1.09,
      "classification": "Average"
    },
    {
      "sector": "Transport & storage",
      "sicSection": "H",
      "employment": 1100,
      "localShare": 0.0336,
      "nationalShare": 0.0508,
      "lq": 0.66,
      "classification": "Under-represented"
    },
    {
      "sector": "Accommodation & food service",
      "sicSection": "I",
      "employment": 3200,
      "localShare": 0.0979,
      "nationalShare": 0.0769,
      "lq": 1.27,
      "classification": "Specialised"
    },
    {
      "sector": "Information & communication",
      "sicSection": "J",
      "employment": 745,
      "localShare": 0.0228,
      "nationalShare": 0.0478,
      "lq": 0.48,
      "classification": "Under-represented"
    },
    {
      "sector": "Financial & insurance",
      "sicSection": "K",
      "employment": 335,
      "localShare": 0.0102,
      "nationalShare": 0.0341,
      "lq": 0.3,
      "classification": "Under-represented"
    },
    {
      "sector": "Real estate",
      "sicSection": "L",
      "employment": 600,
      "localShare": 0.0184,
      "nationalShare": 0.0193,
      "lq": 0.95,
      "classification": "Average"
    },
    {
      "sector": "Professional, scientific & technical",
      "sicSection": "M",
      "employment": 1545,
      "localShare": 0.0473,
      "nationalShare": 0.0963,
      "lq": 0.49,
      "classification": "Under-represented"
    },
    {
      "sector": "Administrative & support services",
      "sicSection": "N",
      "employment": 1230,
      "localShare": 0.0376,
      "nationalShare": 0.0884,
      "lq": 0.43,
      "classification": "Under-represented"
    },
    {
      "sector": "Public administration & defence",
      "sicSection": "O",
      "employment": 2250,
      "localShare": 0.0688,
      "nationalShare": 0.0452,
      "lq": 1.52,
      "classification": "Highly specialised"
    },
    {
      "sector": "Education",
      "sicSection": "P",
      "employment": 2000,
      "localShare": 0.0612,
      "nationalShare": 0.0857,
      "lq": 0.71,
      "classification": "Under-represented"
    },
    {
      "sector": "Human health & social work",
      "sicSection": "Q",
      "employment": 9500,
      "localShare": 0.2906,
      "nationalShare": 0.1375,
      "lq": 2.11,
      "classification": "Highly specialised"
    },
    {
      "sector": "Arts, entertainment & recreation",
      "sicSection": "R",
      "employment": 775,
      "localShare": 0.0237,
      "nationalShare": 0.0242,
      "lq": 0.98,
      "classification": "Average"
    },
    {
      "sector": "Other service activities",
      "sicSection": "S",
      "employment": 355,
      "localShare": 0.0109,
      "nationalShare": 0.0197,
      "lq": 0.55,
      "classification": "Under-represented"
    }
  ],
  "shiftShare": [
    {
      "sector": "Agriculture, forestry & fishing",
      "sicSection": "A",
      "startEmployment": 65,
      "endEmployment": 70,
      "actualChange": 5,
      "nationalShare": 5,
      "industryMix": -15,
      "localCompetitiveness": 16
    },
    {
      "sector": "Mining & quarrying",
      "sicSection": "B",
      "startEmployment": 0,
      "endEmployment": 0,
      "actualChange": 0,
      "nationalShare": 0,
      "industryMix": 0,
      "localCompetitiveness": 0
    },
    {
      "sector": "Manufacturing",
      "sicSection": "C",
      "startEmployment": 2680,
      "endEmployment": 2370,
      "actualChange": -310,
      "nationalShare": 191,
      "industryMix": -231,
      "localCompetitiveness": -270
    },
    {
      "sector": "Electricity, gas & air conditioning",
      "sicSection": "D",
      "startEmployment": 0,
      "endEmployment": 0,
      "actualChange": 0,
      "nationalShare": 0,
      "industryMix": 0,
      "localCompetitiveness": 0
    },
    {
      "sector": "Water supply & waste management",
      "sicSection": "E",
      "startEmployment": 175,
      "endEmployment": 140,
      "actualChange": -35,
      "nationalShare": 12,
      "industryMix": 9,
      "localCompetitiveness": -56
    },
    {
      "sector": "Construction",
      "sicSection": "F",
      "startEmployment": 1350,
      "endEmployment": 1575,
      "actualChange": 225,
      "nationalShare": 96,
      "industryMix": 56,
      "localCompetitiveness": 73
    },
    {
      "sector": "Wholesale & retail trade",
      "sicSection": "G",
      "startEmployment": 5100,
      "endEmployment": 4900,
      "actualChange": -200,
      "nationalShare": 364,
      "industryMix": -450,
      "localCompetitiveness": -114
    },
    {
      "sector": "Transport & storage",
      "sicSection": "H",
      "startEmployment": 900,
      "endEmployment": 1100,
      "actualChange": 200,
      "nationalShare": 64,
      "industryMix": -21,
      "localCompetitiveness": 157
    },
    {
      "sector": "Accommodation & food service",
      "sicSection": "I",
      "startEmployment": 2500,
      "endEmployment": 3200,
      "actualChange": 700,
      "nationalShare": 178,
      "industryMix": 204,
      "localCompetitiveness": 318
    },
    {
      "sector": "Information & communication",
      "sicSection": "J",
      "startEmployment": 600,
      "endEmployment": 745,
      "actualChange": 145,
      "nationalShare": 43,
      "industryMix": 20,
      "localCompetitiveness": 82
    },
    {
      "sector": "Financial & insurance",
      "sicSection": "K",
      "startEmployment": 535,
      "endEmployment": 335,
      "actualChange": -200,
      "nationalShare": 38,
      "industryMix": -22,
      "localCompetitiveness": -216
    },
    {
      "sector": "Real estate",
      "sicSection": "L",
      "startEmployment": 700,
      "endEmployment": 600,
      "actualChange": -100,
      "nationalShare": 50,
      "industryMix": 39,
      "localCompetitiveness": -189
    },
    {
      "sector": "Professional, scientific & technical",
      "sicSection": "M",
      "startEmployment": 1225,
      "endEmployment": 1545,
      "actualChange": 320,
      "nationalShare": 87,
      "industryMix": 90,
      "localCompetitiveness": 142
    },
    {
      "sector": "Administrative & support services",
      "sicSection": "N",
      "startEmployment": 1290,
      "endEmployment": 1230,
      "actualChange": -60,
      "nationalShare": 92,
      "industryMix": -11,
      "localCompetitiveness": -141
    },
    {
      "sector": "Public administration & defence",
      "sicSection": "O",
      "startEmployment": 2000,
      "endEmployment": 2250,
      "actualChange": 250,
      "nationalShare": 143,
      "industryMix": 170,
      "localCompetitiveness": -63
    },
    {
      "sector": "Education",
      "sicSection": "P",
      "startEmployment": 2500,
      "endEmployment": 2000,
      "actualChange": -500,
      "nationalShare": 178,
      "industryMix": -107,
      "localCompetitiveness": -572
    },
    {
      "sector": "Human health & social work",
      "sicSection": "Q",
      "startEmployment": 8000,
      "endEmployment": 9500,
      "actualChange": 1500,
      "nationalShare": 571,
      "industryMix": 386,
      "localCompetitiveness": 543
    },
    {
      "sector": "Arts, entertainment & recreation",
      "sicSection": "R",
      "startEmployment": 775,
      "endEmployment": 775,
      "actualChange": 0,
      "nationalShare": 55,
      "industryMix": 70,
      "localCompetitiveness": -125
    },
    {
      "sector": "Other service activities",
      "sicSection": "S",
      "startEmployment": 415,
      "endEmployment": 355,
      "actualChange": -60,
      "nationalShare": 30,
      "industryMix": 2,
      "localCompetitiveness": -92
    }
  ],
  "startYear": "2020",
  "endYear": "2024"
}